.coveragerc
.editorconfig
.gitignore
.travis.yml
LICENSE
Pipfile
README.md
pyproject.toml
requirements.txt
requirements_dev.txt
setup.cfg
setup.py
.github/workflows/python-publish.yml
democritus_ast.egg-info/PKG-INFO
democritus_ast.egg-info/SOURCES.txt
democritus_ast.egg-info/dependency_links.txt
democritus_ast.egg-info/requires.txt
democritus_ast.egg-info/top_level.txt
democritus_ast.egg-info/zip-safe
democritus_python_data/__init__.py
democritus_python_data/ast_data.py
democritus_python_data/ast_data_temp_utils.py
tests/__init__.py
tests/test_ast_data.py